setup.py
lbry_internet_archive/__init__.py
lbry_internet_archive/main.py
lbry_internet_archive/upload.py
lbry_internet_archive/uploader.py
lbry_internet_archive.egg-info/PKG-INFO
lbry_internet_archive.egg-info/SOURCES.txt
lbry_internet_archive.egg-info/dependency_links.txt
lbry_internet_archive.egg-info/not-zip-safe
lbry_internet_archive.egg-info/top_level.txt