Metadata-Version: 1.0
Name: lbry-internet-archive
Version: 0.2
Summary: A tool to import Internet Archive collections to LBRY
Home-page: https://github.com/marcdeb1/internet-archive
Author: marcdeb
Author-email: marcdebrouchev@laposte.net
License: MIT
Platform: UNKNOWN
